mdod/__init__.py
mdod/mdod.py
mdod-3.0.6.1.dist-info/LICENSE.txt
mdod-3.0.6.1.dist-info/METADATA
mdod-3.0.6.1.dist-info/WHEEL
mdod-3.0.6.1.dist-info/top_level.txt
mdod-3.0.6.1.dist-info/RECORD
