Metadata-Version: 2.1
Name: mdod
Version: 3.0.6.1
Summary: Multi-Dimensional Outlier Detection (MDOD) using vector cosine similarity with added virtual dimension
Home-page: https://github.com/mddod/mdod
Author: Z Shen
Author-email: 626456708@qq.com
License: BSD 3-Clause License
Project-URL: Bug Tracker, https://github.com/mddod/mdod/issues
Project-URL: Documentation, https://mddod.github.io/
Project-URL: Source Code, https://github.com/mddod/mdod
Project-URL: Paper, https://doi.org/10.48550/arXiv.2601.00883
Keywords: outlier detection,anomaly detection,multi-dimensional data,cosine similarity,machine learning,data mining,unsupervised learning,scikit-learn,python,AI
Classifier: Development Status :: 5 - Production/Stable
Classifier: Intended Audience :: Developers
Classifier: Intended Audience :: Science/Research
Classifier: Topic :: Scientific/Engineering :: Artificial Intelligence
Classifier: Topic :: Scientific/Engineering :: Information Analysis
Classifier: License :: OSI Approved :: BSD License
Classifier: Operating System :: OS Independent
Classifier: Programming Language :: Python
Classifier: Programming Language :: Python :: 3
Classifier: Programming Language :: Python :: 3.7
Classifier: Programming Language :: Python :: 3.8
Classifier: Programming Language :: Python :: 3.9
Classifier: Programming Language :: Python :: 3.10
Classifier: Programming Language :: Python :: 3.11
Classifier: Programming Language :: Python :: 3.12
Requires-Python: >=3.7
License-File: LICENSE.txt
Requires-Dist: numpy>=1.21.0
Requires-Dist: scipy>=1.7.0
Requires-Dist: scikit-learn>=1.0.0
